starling_server/__init__.py
starling_server/cli/__init__.py
starling_server/cli/cli.py
starling_server/config.py
starling_server/main.py
starling_server/models/Account.py
starling_server/models/Transaction.py
starling_server/models/__init__.py
starling_server/starling/__init__.py
starling_server/starling/api.py
starling_server/starling/models/StarlingAccount.py
starling_server/starling/models/StarlingTransaction.py
starling_server/starling/models/__init__.py
starling_server/starling/utils.py
starling_server-0.1.2.dist-info/entry_points.txt
starling_server-0.1.2.dist-info/LICENSE.md
starling_server-0.1.2.dist-info/WHEEL
starling_server-0.1.2.dist-info/METADATA
starling_server-0.1.2.dist-info/RECORD
